dreamy_utilities/Configuration.py
dreamy_utilities/Containers.py
dreamy_utilities/Filesystem.py
dreamy_utilities/HTML.py
dreamy_utilities/Interface.py
dreamy_utilities/Mathematics.py
dreamy_utilities/Text.py
dreamy_utilities/Web.py
dreamy_utilities/WebSession.py
dreamy_utilities/__init__.py
Dreamy_Utilities-1.2.0.dist-info/LICENSE
Dreamy_Utilities-1.2.0.dist-info/METADATA
Dreamy_Utilities-1.2.0.dist-info/WHEEL
Dreamy_Utilities-1.2.0.dist-info/top_level.txt
Dreamy_Utilities-1.2.0.dist-info/RECORD
