Metadata-Version: 2.1
Name: Dreamy-Utilities
Version: 1.2.0
Summary: A collection of various utilities. 
Home-page: https://github.com/DreamCobbler/dreamy-utilities
Author: Benedykt Synakiewicz
Author-email: dreamcobbler@outlook.com
License: UNKNOWN
Platform: UNKNOWN
Classifier: Development Status :: 5 - Production/Stable
Classifier: Programming Language :: Python :: 3
Classifier: License :: OSI Approved :: GNU General Public License (GPL)
Classifier: Operating System :: OS Independent
Classifier: Intended Audience :: Developers
Requires-Python: >=3.8
Requires-Dist: babel
Requires-Dist: bs4
Requires-Dist: cloudscraper
Requires-Dist: colorama
Requires-Dist: termtables
Requires-Dist: titlecase
Requires-Dist: tldextract
